formiodata/builder.py
formiodata/components/__init__.py
formiodata/components/address.py
formiodata/components/button.py
formiodata/components/checkbox.py
formiodata/components/columns.py
formiodata/components/component.py
formiodata/components/content.py
formiodata/components/currency.py
formiodata/components/datagrid.py
formiodata/components/datetime.py
formiodata/components/day.py
formiodata/components/editgrid.py
formiodata/components/email.py
formiodata/components/fieldset.py
formiodata/components/file.py
formiodata/components/grid_base.py
formiodata/components/htmlelement.py
formiodata/components/layout_base.py
formiodata/components/number.py
formiodata/components/panel.py
formiodata/components/password.py
formiodata/components/phoneNumber.py
formiodata/components/phone_number.py
formiodata/components/radio.py
formiodata/components/resource.py
formiodata/components/select.py
formiodata/components/selectboxes.py
formiodata/components/signature.py
formiodata/components/survey.py
formiodata/components/table.py
formiodata/components/tabs.py
formiodata/components/textarea.py
formiodata/components/textfield.py
formiodata/components/time.py
formiodata/components/url.py
formiodata/form.py
formiodata/utils.py
formio_data-2.1.6.dist-info/LICENSE
formio_data-2.1.6.dist-info/METADATA
formio_data-2.1.6.dist-info/WHEEL
formio_data-2.1.6.dist-info/RECORD
