Metadata-Version: 2.3
Name: formio-data
Version: 2.1.6
Summary: formio.js JSON-data API
License: MIT
Author: Bob Leers
Author-email: bob@novacode.nl
Requires-Python: >=3.6,<4.0
Classifier: License :: OSI Approved :: MIT License
Classifier: Programming Language :: Python :: 3
Classifier: Programming Language :: Python :: 3.6
Classifier: Programming Language :: Python :: 3.7
Classifier: Programming Language :: Python :: 3.8
Classifier: Programming Language :: Python :: 3.9
Classifier: Programming Language :: Python :: 3.10
Classifier: Programming Language :: Python :: 3.11
Classifier: Programming Language :: Python :: 3.12
Classifier: Programming Language :: Python :: 3.13
Provides-Extra: json-logic
Requires-Dist: json_logic_qubit (>=0.9.1,<0.10.0) ; extra == "json-logic"
Requires-Dist: python-dateutil (>=2.8.2,<3.0.0) ; python_full_version <= "3.6.0"
Requires-Dist: requests
Project-URL: Homepage, https://github.com/novacode-nl/python-formio-data
